{"stats":{"minecraft:broken":{"aether:leather_gloves":1},"minecraft:mined":{"minecraft:white_bed":8,"quark:yellow_blossom_leaves":1,"minecraft:blast_furnace":2,"minecraft:crafting_table":3,"luminousworld:mossbuds_2":1,"minecraft:grass_block":4,"minecraft:chest":1,"minecraft:rose_bush":1,"minecraft:coal_block":27,"minecraft:tall_grass":1,"minecraft:spruce_leaves":3,"minecraft:spawner":6,"minecraft:large_fern":1,"minecraft:spruce_stairs":1,"minecraft:hay_block":51,"minecraft:furnace":2,"ecologics:seashell":1,"minecraft:birch_log":1,"minecraft:wheat":15,"minecraft:red_wall_banner":1,"minecraft:brown_bed":5,"minecraft:grass":3,"minecraft:oak_log":10,"minecraft:lantern":1,"minecraft:dirt":1,"minecraft:cobweb":4,"luminousworld:grassvariant_3":1,"minecraft:stone":3,"minecraft:iron_block":3,"minecraft:oak_leaves":1},"minecraft:crafted":{"minecraft:oak_door":3,"minecraft:oak_planks":36,"sophisticatedbackpacks:backpack":1,"minecraft:crafting_table":2,"minecraft:wooden_pickaxe":1,"sophisticatedbackpacks:gold_backpack":1,"minecraft:birch_planks":4,"minecraft:bread":96,"minecraft:shield":1,"minecraft:iron_axe":1,"minecraft:stick":8,"minecraft:iron_ingot":27,"minecraft:stone_pickaxe":1,"minecraft:wooden_axe":2,"minecraft:wheat":288,"sophisticatedbackpacks:iron_backpack":1},"minecraft:picked_up":{"minecraft:birch_log":1,"minecraft:iron_chestplate":4,"luminousworld:groundpebbles_1":1,"minecraft:crafting_table":3,"minecraft:wheat":10,"minecraft:leather":1,"minecraft:golden_leggings":6,"minecraft:wooden_pickaxe":1,"minecraft:brown_bed":5,"minecraft:oak_log":9,"aether:leather_gloves":1,"minecraft:string":8,"minecraft:dirt":5,"minecraft:lantern":3,"minecraft:iron_axe":1,"minecraft:iron_leggings":4,"minecraft:armor_stand":8,"minecraft:bone":4,"minecraft:experience_bottle":1,"minecraft:bow":2,"minecraft:wheat_seeds":32,"minecraft:iron_ingot":6,"minecraft:stone_pickaxe":1,"minecraft:rose_bush":1,"minecraft:iron_pickaxe":1,"minecraft:coal_block":27,"minecraft:chest":1,"minecraft:iron_sword":2,"minecraft:iron_boots":4,"minecraft:furnace":2,"minecraft:golden_helmet":6,"minecraft:stick":4,"born_in_chaos_v1:ethereal_spirit":2,"minecraft:spruce_stairs":1,"minecraft:blast_furnace":2,"minecraft:red_banner":1,"minecraft:white_bed":8,"tombstone:grave_dust":1,"born_in_chaos_v1:pieceofdarkmetal":1,"minecraft:stone_pressure_plate":2,"minecraft:rotten_flesh":8,"minecraft:hay_block":52,"minecraft:iron_helmet":3,"minecraft:iron_block":3,"minecraft:carved_pumpkin":1,"minecraft:gray_wool":1,"minecraft:emerald":1,"minecraft:mutton":4,"minecraft:coal":15,"minecraft:white_wool":2,"minecraft:cobblestone":3,"minecraft:wooden_axe":1},"minecraft:dropped":{"minecraft:oak_door":1,"minecraft:iron_ingot":6,"minecraft:bread":39,"minecraft:wheat_seeds":32,"minecraft:golden_helmet":6,"minecraft:bowl":1,"minecraft:wheat":14,"born_in_chaos_v1:ethereal_spirit":2,"minecraft:iron_helmet":1,"minecraft:rotten_flesh":2,"aether:leather_gloves":1,"minecraft:iron_boots":1,"minecraft:stick":2,"minecraft:gray_wool":1,"minecraft:iron_chestplate":1,"luminousworld:groundpebbles_1":1,"minecraft:wooden_axe":2,"minecraft:rose_bush":1,"minecraft:golden_leggings":6,"tombstone:grave_dust":1,"minecraft:iron_leggings":1,"minecraft:bow":1,"minecraft:stone_pickaxe":1,"minecraft:wooden_pickaxe":1,"minecraft:string":2,"minecraft:white_wool":2,"minecraft:armor_stand":8},"minecraft:used":{"minecraft:stone_pickaxe":15,"minecraft:oak_planks":7,"minecraft:wooden_pickaxe":8,"minecraft:shield":17,"minecraft:iron_sword":166,"minecraft:oak_door":2,"minecraft:dirt":5,"minecraft:mutton":4,"minecraft:crafting_table":4,"minecraft:spruce_stairs":1,"minecraft:white_bed":6,"minecraft:wooden_axe":47,"minecraft:iron_axe":16,"minecraft:bread":28,"minecraft:suspicious_stew":1,"minecraft:iron_pickaxe":21,"minecraft:brown_bed":4},"minecraft:killed":{"born_in_chaos_v1:restless_spirit":1,"born_in_chaos_v1:door_knight_not_despawn":2,"born_in_chaos_v1:pumpkin_spirit":1,"minecraft:spider":3,"born_in_chaos_v1:decrepit_skeleton":4,"minecraft:sheep":3,"born_in_chaos_v1:corpse_fish":1},"minecraft:custom":{"minecraft:interact_with_furnace":1,"minecraft:mob_kills":15,"minecraft:interact_with_crafting_table":9,"minecraft:open_barrel":18,"minecraft:bell_ring":4,"minecraft:damage_dealt_resisted":1127,"minecraft:leave_game":9,"minecraft:time_since_death":109164,"minecraft:sleep_in_bed":9,"minecraft:climb_one_cm":2517,"minecraft:time_since_rest":2708,"minecraft:sprint_one_cm":355921,"minecraft:damage_taken":1122,"minecraft:walk_one_cm":317268,"minecraft:damage_blocked_by_shield":484,"minecraft:drop":43,"minecraft:damage_dealt":4791,"minecraft:swim_one_cm":47646,"minecraft:fly_one_cm":365251,"minecraft:open_chest":36,"minecraft:crouch_one_cm":3833,"minecraft:play_time":109164,"tombstone:undead_killed":6,"minecraft:sneak_time":1705,"minecraft:walk_under_water_one_cm":13921,"minecraft:jump":1584,"minecraft:walk_on_water_one_cm":15130,"minecraft:total_world_time":109164,"minecraft:fall_one_cm":43667}},"DataVersion":3465}